nn_fac/__init__.py
nn_fac/deep_nmf.py
nn_fac/min_vol_nmf.py
nn_fac/multilayer_nmf.py
nn_fac/nmf.py
nn_fac/ntd.py
nn_fac/ntf.py
nn_fac/parafac2.py
nn_fac/simplex_nmf.py
nn_fac/update_rules/__init__.py
nn_fac/update_rules/deep_mu.py
nn_fac/update_rules/min_vol_mu.py
nn_fac/update_rules/mu.py
nn_fac/update_rules/nnls.py
nn_fac/utils/__init__.py
nn_fac/utils/beta_divergence.py
nn_fac/utils/errors.py
nn_fac/utils/normalize_wh.py
nn_fac-0.3.4.dist-info/AUTHORS
nn_fac-0.3.4.dist-info/LICENSE
nn_fac-0.3.4.dist-info/METADATA
nn_fac-0.3.4.dist-info/WHEEL
nn_fac-0.3.4.dist-info/top_level.txt
nn_fac-0.3.4.dist-info/RECORD
