Metadata-Version: 2.1
Name: nn-fac
Version: 0.3.4
Summary: Nonnegative factorization toolbox.
Home-page: https://gitlab.imt-atlantique.fr/a23marmo/nonnegative-factorization/
Author: Marmoret Axel
Author-email: axel.marmoret@irisa.fr
License: BSD
Classifier: License :: OSI Approved :: BSD License
Classifier: Programming Language :: Python
Classifier: Development Status :: 3 - Alpha
Classifier: Intended Audience :: Developers
Classifier: Intended Audience :: Science/Research
Classifier: Topic :: Scientific/Engineering :: Mathematics
Classifier: Topic :: Scientific/Engineering :: Artificial Intelligence
Classifier: Programming Language :: Python :: 3.7
Requires-Python: >=3.7
License-File: LICENSE
License-File: AUTHORS
Requires-Dist: nimfa
Requires-Dist: numpy >=1.18.0
Requires-Dist: scipy >=0.13.0
Requires-Dist: tensorly ==0.6.0
